unpythonic-0.15.5.dist-info/METADATA
unpythonic-0.15.5.dist-info/WHEEL
unpythonic-0.15.5.dist-info/entry_points.txt
unpythonic-0.15.5.dist-info/licenses/LICENSE.md
unpythonic/__init__.py
unpythonic/amb.py
unpythonic/arity.py
unpythonic/assignonce.py
unpythonic/collections.py
unpythonic/conditions.py
unpythonic/dialects/__init__.py
unpythonic/dialects/lispython.py
unpythonic/dialects/listhell.py
unpythonic/dialects/pytkell.py
unpythonic/dispatch.py
unpythonic/dynassign.py
unpythonic/ec.py
unpythonic/env.py
unpythonic/excutil.py
unpythonic/fix.py
unpythonic/fold.py
unpythonic/fploop.py
unpythonic/fun.py
unpythonic/funutil.py
unpythonic/fup.py
unpythonic/gmemo.py
unpythonic/gtco.py
unpythonic/it.py
unpythonic/lazyutil.py
unpythonic/let.py
unpythonic/lispylet.py
unpythonic/llist.py
unpythonic/mathseq.py
unpythonic/misc.py
unpythonic/net/__init__.py
unpythonic/net/client.py
unpythonic/net/common.py
unpythonic/net/msg.py
unpythonic/net/ptyproxy.py
unpythonic/net/server.py
unpythonic/net/util.py
unpythonic/numutil.py
unpythonic/regutil.py
unpythonic/seq.py
unpythonic/singleton.py
unpythonic/slicing.py
unpythonic/symbol.py
unpythonic/syntax/00_stuff/letdo.py
unpythonic/syntax/__init__.py
unpythonic/syntax/autocurry.py
unpythonic/syntax/autoref.py
unpythonic/syntax/dbg.py
unpythonic/syntax/forall.py
unpythonic/syntax/ifexprs.py
unpythonic/syntax/lambdatools.py
unpythonic/syntax/lazify.py
unpythonic/syntax/letdo.py
unpythonic/syntax/letdoutil.py
unpythonic/syntax/letsyntax.py
unpythonic/syntax/nameutil.py
unpythonic/syntax/nb.py
unpythonic/syntax/prefix.py
unpythonic/syntax/scopeanalyzer.py
unpythonic/syntax/simplelet.py
unpythonic/syntax/tailtools.py
unpythonic/syntax/testingtools.py
unpythonic/syntax/util.py
unpythonic/tco.py
unpythonic/test/fixtures.py
unpythonic/timeutil.py
unpythonic/typecheck.py
unpythonic-0.15.5.dist-info/RECORD
