Metadata-Version: 2.1
Name: unpythonic
Version: 0.15.5
Summary: Supercharge your Python with parts of Lisp and Haskell.
Keywords: functional-programming,language-extension,syntactic-macros,tail-call-optimization,tco,continuations,currying,lazy-evaluation,dynamic-variable,macros,lisp,scheme,racket,haskell
Author-Email: Juha Jeronen <juha.m.jeronen@gmail.com>
License: BSD
Classifier: Development Status :: 4 - Beta
Classifier: Environment :: Console
Classifier: Intended Audience :: Developers
Classifier: License :: OSI Approved :: BSD License
Classifier: Operating System :: POSIX :: Linux
Classifier: Programming Language :: Python
Classifier: Programming Language :: Python :: 3
Classifier: Programming Language :: Python :: 3.8
Classifier: Programming Language :: Python :: 3.9
Classifier: Programming Language :: Python :: 3.10
Classifier: Programming Language :: Python :: 3.11
Classifier: Programming Language :: Python :: 3.12
Classifier: Programming Language :: Python :: Implementation :: CPython
Classifier: Programming Language :: Python :: Implementation :: PyPy
Classifier: Topic :: Software Development :: Libraries
Classifier: Topic :: Software Development :: Libraries :: Python Modules
Project-URL: Repository, https://github.com/Technologicat/unpythonic
Requires-Python: <3.13,>=3.8
Requires-Dist: mcpyrate>=3.6.4
Requires-Dist: sympy>=1.13
